{
	"animations": [
		{
			"offsets": [
				40,
				-18
			],
			"loop": false,
			"fps": 24,
			"anim": "singLEFT",
			"indices": [],
			"name": "left"
		},
		{
			"offsets": [
				93,
				-60
			],
			"loop": false,
			"fps": 24,
			"anim": "singDOWN",
			"indices": [],
			"name": "down"
		},
		{
			"offsets": [
				-21,
				30
			],
			"loop": false,
			"fps": 24,
			"anim": "singUP",
			"indices": [],
			"name": "up"
		},
		{
			"offsets": [
				-6,
				-11
			],
			"loop": false,
			"fps": 24,
			"anim": "singRIGHT",
			"indices": [],
			"name": "right"
		},
		{
			"offsets": [
				140,
				-18
			],
			"loop": false,
			"fps": 24,
			"anim": "singLEFTmiss",
			"indices": [],
			"name": "rMISSleft"
		},
		{
			"offsets": [
				103,
				-59
			],
			"loop": false,
			"fps": 24,
			"anim": "singDOWNmiss",
			"indices": [],
			"name": "rMISSdown"
		},
		{
			"offsets": [
				-21,
				30
			],
			"loop": false,
			"fps": 24,
			"anim": "singUPmiss",
			"indices": [],
			"name": "rMISSup"
		},
		{
			"offsets": [
				-6,
				-11
			],
			"loop": false,
			"fps": 24,
			"anim": "singRIGHTmiss",
			"indices": [],
			"name": "rMISSright"
		},
		{
			"loop": false,
			"offsets": [
				0,
				0
			],
			"anim": "danceRight",
			"fps": 24,
			"name": "idle",
			"indices": [
				0,
				1,
				2,
				3,
				4,
				5,
				6,
				7,
				8,
				9,
				10
			]
		},
		{
			"loop": false,
			"offsets": [
				0,
				0
			],
			"anim": "danceLeft",
			"fps": 24,
			"name": "idle",
			"indices": [
				11,
				12,
				13,
				14,
				15,
				16,
				17,
				18,
				19,
				20,
				21,
				22
			]
		}
	],
	"no_antialiasing": false,
	"image": "characters/bella-1/bella1",
	"position": [
		0,
		0
	],
	"healthicon": "bella",
	"flip_x": false,
	"healthbar_colors": [
		255,
		255,
		255
	],
	"camera_position": [
		-130,
		310
	],
	"sing_duration": 6.1,
	"scale": 1,
	"note_colors": [-22, -50, 13]
}